armstrong_checker/__init__.py
armstrong_checker/checker.py
armstrong_checker-0.1.5.dist-info/METADATA
armstrong_checker-0.1.5.dist-info/WHEEL
armstrong_checker-0.1.5.dist-info/top_level.txt
armstrong_checker-0.1.5.dist-info/RECORD
