Metadata-Version: 2.4
Name: armstrong-checker
Version: 0.1.5
Summary: Library to check if a number is Armstrong
Author: João Pedro Calaça Costa
Classifier: Programming Language :: Python :: 3
Classifier: Operating System :: OS Independent
Requires-Python: >=3.6
Dynamic: author
Dynamic: classifier
Dynamic: description
Dynamic: description-content-type
Dynamic: requires-python
Dynamic: summary
